thundradebugclient/__init__.py
thundradebugclient/__main__.py
thundradebugclient/_version.py
thundradebugclient/constants.py
thundradebugclient/debugger_agent.py
thundradebugclient/debugger_config.py
thundradebugclient/data/debug-client.json
thundra_debug_client-1.0.3.dist-info/METADATA
thundra_debug_client-1.0.3.dist-info/WHEEL
thundra_debug_client-1.0.3.dist-info/entry_points.txt
thundra_debug_client-1.0.3.dist-info/top_level.txt
thundra_debug_client-1.0.3.dist-info/zip-safe
thundra_debug_client-1.0.3.dist-info/RECORD
